telemetry_f1_2021/__init__.py
telemetry_f1_2021/cleaned_packets.py
telemetry_f1_2021/listener.py
telemetry_f1_2021/main.py
telemetry_f1_2021/packets.py
telemetry_f1_2021/example_packets/__init__.py
telemetry_f1_2021/example_packets/loader.py
telemetry_f1_2021/example_packets/json/__init__.py
Telemetry_F1_2021-0.3.0.dist-info/LICENSE
Telemetry_F1_2021-0.3.0.dist-info/METADATA
Telemetry_F1_2021-0.3.0.dist-info/WHEEL
Telemetry_F1_2021-0.3.0.dist-info/entry_points.txt
Telemetry_F1_2021-0.3.0.dist-info/top_level.txt
Telemetry_F1_2021-0.3.0.dist-info/RECORD
