Metadata-Version: 2.1
Name: Telemetry-F1-2021
Version: 0.3.0
Summary: Decode F1 2021 telemetry data.
Home-page: https://github.com/chrishannam/Telemetry-F1-2021
Author: Chris Hannam
Author-email: ch@chrishannam.co.uk
License: UNKNOWN
Platform: UNKNOWN
Classifier: Programming Language :: Python :: 3
Classifier: License :: OSI Approved :: Apache Software License
Classifier: Operating System :: OS Independent
Requires-Python: >=3.6
License-File: LICENSE
